{
  "forge_marker" : 1,
  "defaults" : {
    "model" : "cube_all"
  },
  "variants" : {
    "soiltype" : {
      "silt" : {
        "textures" : {
          "all" : "tfc:blocks/soil/clay/silt"
        }
      },
      "loam" : {
        "textures" : {
          "all" : "tfc:blocks/soil/clay/loam"
        }
      },
      "sandy_loam" : {
        "textures" : {
          "all" : "tfc:blocks/soil/clay/sandy_loam"
        }
      },
      "silty_loam" : {
        "textures" : {
          "all" : "tfc:blocks/soil/clay/silty_loam"
        }
      }
    }
  }
}
